{
  "gender": "female",
  "name": {
    "title": "Ms",
    "first": "Jade",
    "last": "Scott"
  },
  "location": {
    "street": {
      "number": 9809,
      "name": "George St"
    },
    "city": "Sutton",
    "state": "Nunavut",
    "country": "Canada",
    "postcode": "O2J 7L2",
    "coordinates": {
      "latitude": "-69.1890",
      "longitude": "63.8329"
    },
    "timezone": {
      "offset": "-10:00",
      "description": "Hawaii"
    }
  },
  "email": "jade.scott@example.com",
  "login": {
    "uuid": "9da1f8e9-ff0a-4469-9019-1e3db2b2f5d4",
    "username": "organicbutterfly934",
    "password": "alfredo",
    "salt": "0cNqzL1b",
    "md5": "6f047f27ae9d5477f529724afc1bc41c",
    "sha1": "d3debfafd28545fa1994d26952d36271ff6cd472",
    "sha256": "f3a9e64297614d8e5a1a11382ff9e8910b5d528a0f363472f2df6b0e128961db"
  },
  "dob": {
    "date": "1957-06-11T02:15:22.333Z",
    "age": 67
  },
  "registered": {
    "date": "2019-05-01T11:32:48.328Z",
    "age": 5
  },
  "phone": "D71 Y38-3520",
  "cell": "W47 X78-4992",
  "id": {
    "name": "SIN",
    "value": "975044371"
  },
  "picture": {
    "large": "https://randomuser.me/api/portraits/women/70.jpg",
    "medium": "https://randomuser.me/api/portraits/med/women/70.jpg",
    "thumbnail": "https://randomuser.me/api/portraits/thumb/women/70.jpg"
  },
  "nat": "CA"
}