{
  "gender": "female",
  "name": {
    "title": "Ms",
    "first": "Miriam",
    "last": "Santiago"
  },
  "location": {
    "street": {
      "number": 222,
      "name": "Avenida de Castilla"
    },
    "city": "Ferrol",
    "state": "La Rioja",
    "country": "Spain",
    "postcode": 23973,
    "coordinates": {
      "latitude": "-36.9868",
      "longitude": "81.8036"
    },
    "timezone": {
      "offset": "-1:00",
      "description": "Azores, Cape Verde Islands"
    }
  },
  "email": "miriam.santiago@example.com",
  "login": {
    "uuid": "add6014b-299b-4384-9bee-924b34bf428e",
    "username": "whitemeercat228",
    "password": "toriamos",
    "salt": "LLToHqtR",
    "md5": "323d0355f4e1a06a9d43996e81662240",
    "sha1": "f942c5d91b59722104d13d9a0e8afe831399fa15",
    "sha256": "4a23c0f0d990c9374db91274a31f48ce1ddefe5225c7461f17d66fc2c0bff3f2"
  },
  "dob": {
    "date": "1959-08-21T18:39:30.910Z",
    "age": 65
  },
  "registered": {
    "date": "2016-03-30T23:02:48.817Z",
    "age": 8
  },
  "phone": "937-921-599",
  "cell": "640-408-887",
  "id": {
    "name": "DNI",
    "value": "25408037-E"
  },
  "picture": {
    "large": "https://randomuser.me/api/portraits/women/18.jpg",
    "medium": "https://randomuser.me/api/portraits/med/women/18.jpg",
    "thumbnail": "https://randomuser.me/api/portraits/thumb/women/18.jpg"
  },
  "nat": "ES"
}