{
  "gender": "female",
  "name": {
    "title": "Ms",
    "first": "Vildan",
    "last": "Sözeri"
  },
  "location": {
    "street": {
      "number": 1410,
      "name": "Maçka Cd"
    },
    "city": "Afyonkarahisar",
    "state": "Aksaray",
    "country": "Turkey",
    "postcode": 95204,
    "coordinates": {
      "latitude": "68.7228",
      "longitude": "25.1507"
    },
    "timezone": {
      "offset": "+3:00",
      "description": "Baghdad, Riyadh, Moscow, St. Petersburg"
    }
  },
  "email": "vildan.sozeri@example.com",
  "login": {
    "uuid": "fbf82b0d-fcd0-4659-a8eb-f6cc347f8f6f",
    "username": "sadzebra483",
    "password": "tracker",
    "salt": "YZaAvKOI",
    "md5": "f3dbeae5436179653a5ea1e114abfa76",
    "sha1": "9ac91c192a7a9f2d990ccd70435bf5888e995893",
    "sha256": "3fa412d2a4740b351bdd955fa3d3a8cd42fa6effbd0680478bd4d4aa217e67d5"
  },
  "dob": {
    "date": "1989-10-10T14:16:45.645Z",
    "age": 35
  },
  "registered": {
    "date": "2018-06-23T18:14:43.675Z",
    "age": 6
  },
  "phone": "(249)-594-9894",
  "cell": "(406)-080-1343",
  "id": {
    "name": "",
    "value": null
  },
  "picture": {
    "large": "https://randomuser.me/api/portraits/women/21.jpg",
    "medium": "https://randomuser.me/api/portraits/med/women/21.jpg",
    "thumbnail": "https://randomuser.me/api/portraits/thumb/women/21.jpg"
  },
  "nat": "TR"
}