{
  "gender": "male",
  "name": {
    "title": "Mr",
    "first": "Oles",
    "last": "Lazor"
  },
  "location": {
    "street": {
      "number": 3826,
      "name": "Ploshcha Malanyuka"
    },
    "city": "Novoyavorivsk",
    "state": "Avtonomna Respublika Krim",
    "country": "Ukraine",
    "postcode": 57170,
    "coordinates": {
      "latitude": "79.1374",
      "longitude": "-2.3159"
    },
    "timezone": {
      "offset": "+3:30",
      "description": "Tehran"
    }
  },
  "email": "oles.lazor@example.com",
  "login": {
    "uuid": "97968908-5a6e-4f60-bfd5-d7e1339d0b22",
    "username": "ticklishfrog877",
    "password": "wally",
    "salt": "wOB50zcC",
    "md5": "5ef1c8d16a0c3a1f3ce90ec0cb5b61ca",
    "sha1": "c3ded6279dce89b808a37e24da3c9b69270aad8f",
    "sha256": "9a0d0e23fed89e0af640419efa5ac674511df542397f9ef047571dfced2b2f93"
  },
  "dob": {
    "date": "1970-08-16T01:23:58.481Z",
    "age": 54
  },
  "registered": {
    "date": "2019-12-07T18:54:24.524Z",
    "age": 5
  },
  "phone": "(067) F68-0711",
  "cell": "(068) D49-3593",
  "id": {
    "name": "",
    "value": null
  },
  "picture": {
    "large": "https://randomuser.me/api/portraits/men/11.jpg",
    "medium": "https://randomuser.me/api/portraits/med/men/11.jpg",
    "thumbnail": "https://randomuser.me/api/portraits/thumb/men/11.jpg"
  },
  "nat": "UA"
}