{
  "gender": "male",
  "name": {
    "title": "Mr",
    "first": "Noah",
    "last": "Bouchard"
  },
  "location": {
    "street": {
      "number": 357,
      "name": "Dieppe Ave"
    },
    "city": "Campbellton",
    "state": "Saskatchewan",
    "country": "Canada",
    "postcode": "K8C 2V8",
    "coordinates": {
      "latitude": "-70.6548",
      "longitude": "-98.1911"
    },
    "timezone": {
      "offset": "+3:00",
      "description": "Baghdad, Riyadh, Moscow, St. Petersburg"
    }
  },
  "email": "noah.bouchard@example.com",
  "login": {
    "uuid": "b18051e7-7f16-4a90-ba79-7bfd19755de7",
    "username": "lazymouse537",
    "password": "nike",
    "salt": "E7fAQMb0",
    "md5": "d9316c161c4be949298a14c5feb2dd87",
    "sha1": "74b0d19f41e8e46ede677a49cf2f13c6f8350401",
    "sha256": "784f12c34c84287cd9f9d9116ec9bc8772b2e9f915b16b59277e27875ee66ed1"
  },
  "dob": {
    "date": "1984-09-02T18:18:51.560Z",
    "age": 40
  },
  "registered": {
    "date": "2021-05-10T00:19:33.250Z",
    "age": 3
  },
  "phone": "C54 I38-9457",
  "cell": "E45 P67-7451",
  "id": {
    "name": "SIN",
    "value": "628719239"
  },
  "picture": {
    "large": "https://randomuser.me/api/portraits/men/84.jpg",
    "medium": "https://randomuser.me/api/portraits/med/men/84.jpg",
    "thumbnail": "https://randomuser.me/api/portraits/thumb/men/84.jpg"
  },
  "nat": "CA"
}