{
  "gender": "female",
  "name": {
    "title": "Mrs",
    "first": "Teodora",
    "last": "Miljković"
  },
  "location": {
    "street": {
      "number": 912,
      "name": "Doljanska"
    },
    "city": "Valjevo",
    "state": "Kolubara",
    "country": "Serbia",
    "postcode": 44845,
    "coordinates": {
      "latitude": "59.0363",
      "longitude": "56.5629"
    },
    "timezone": {
      "offset": "-2:00",
      "description": "Mid-Atlantic"
    }
  },
  "email": "teodora.miljkovic@example.com",
  "login": {
    "uuid": "d66612e2-6025-42de-9f1c-5d2e69861c77",
    "username": "silverfrog862",
    "password": "allsop",
    "salt": "cjtkY5K7",
    "md5": "155134b666714c71a7f064e715bd6fbc",
    "sha1": "51d53283b597cc92b94e66d3f2387788a2f3c7d4",
    "sha256": "fbad768d99c1d7684f287951fd684aba696693dd641665eb5577b110fb51399b"
  },
  "dob": {
    "date": "1954-01-26T21:11:35.111Z",
    "age": 71
  },
  "registered": {
    "date": "2019-11-17T22:43:18.632Z",
    "age": 5
  },
  "phone": "025-4074-451",
  "cell": "065-3892-693",
  "id": {
    "name": "SID",
    "value": "921610875"
  },
  "picture": {
    "large": "https://randomuser.me/api/portraits/women/41.jpg",
    "medium": "https://randomuser.me/api/portraits/med/women/41.jpg",
    "thumbnail": "https://randomuser.me/api/portraits/thumb/women/41.jpg"
  },
  "nat": "RS"
}