{
  "gender": "female",
  "name": {
    "title": "Miss",
    "first": "Emily",
    "last": "Park"
  },
  "location": {
    "street": {
      "number": 6234,
      "name": "Simcoe St"
    },
    "city": "Jasper",
    "state": "Manitoba",
    "country": "Canada",
    "postcode": "W2L 5M1",
    "coordinates": {
      "latitude": "-69.9919",
      "longitude": "65.2202"
    },
    "timezone": {
      "offset": "+4:30",
      "description": "Kabul"
    }
  },
  "email": "emily.park@example.com",
  "login": {
    "uuid": "6b1a9d72-cd29-40d7-918b-617fd256df4c",
    "username": "silvergorilla205",
    "password": "loretta",
    "salt": "1kMd1Dwg",
    "md5": "d6507bd83f71703f873bdeb1d1e5db58",
    "sha1": "9595041480782bb01545090eec0c0e1d82b0f61b",
    "sha256": "44f4f357cd49e1b7172ce97c7a42c35048f6fd917ed324cd085a0466bb3ac316"
  },
  "dob": {
    "date": "1972-05-20T06:34:43.918Z",
    "age": 52
  },
  "registered": {
    "date": "2021-02-27T13:56:15.104Z",
    "age": 4
  },
  "phone": "D34 V93-7257",
  "cell": "B51 O86-8571",
  "id": {
    "name": "SIN",
    "value": "032945198"
  },
  "picture": {
    "large": "https://randomuser.me/api/portraits/women/83.jpg",
    "medium": "https://randomuser.me/api/portraits/med/women/83.jpg",
    "thumbnail": "https://randomuser.me/api/portraits/thumb/women/83.jpg"
  },
  "nat": "CA"
}