{
  "gender": "female",
  "name": {
    "title": "Ms",
    "first": "Melina",
    "last": "Bjelica"
  },
  "location": {
    "street": {
      "number": 9105,
      "name": "Mramoračka"
    },
    "city": "Sombor",
    "state": "Braničevo",
    "country": "Serbia",
    "postcode": 40701,
    "coordinates": {
      "latitude": "60.8351",
      "longitude": "18.3561"
    },
    "timezone": {
      "offset": "+9:30",
      "description": "Adelaide, Darwin"
    }
  },
  "email": "melina.bjelica@example.com",
  "login": {
    "uuid": "80aee9c1-5119-4877-bcc7-ae4f154cff86",
    "username": "heavyostrich930",
    "password": "russia",
    "salt": "fhMGCE9V",
    "md5": "d1d5ad24fe0ebb856edf12f59c0d5673",
    "sha1": "d371d72f1bde75f26fd23a13863290dee3f5842e",
    "sha256": "d563d0f178a8f1eab8fb51fc7aa5121b02340ce034753836ae775c74df1e9b98"
  },
  "dob": {
    "date": "1961-04-27T00:58:39.331Z",
    "age": 63
  },
  "registered": {
    "date": "2021-05-31T16:45:01.527Z",
    "age": 3
  },
  "phone": "022-7995-496",
  "cell": "069-5850-670",
  "id": {
    "name": "SID",
    "value": "724824599"
  },
  "picture": {
    "large": "https://randomuser.me/api/portraits/women/7.jpg",
    "medium": "https://randomuser.me/api/portraits/med/women/7.jpg",
    "thumbnail": "https://randomuser.me/api/portraits/thumb/women/7.jpg"
  },
  "nat": "RS"
}