{
  "gender": "male",
  "name": {
    "title": "Mr",
    "first": "Tommy",
    "last": "Bailey"
  },
  "location": {
    "street": {
      "number": 6714,
      "name": "Paddock Way"
    },
    "city": "Geelong",
    "state": "Victoria",
    "country": "Australia",
    "postcode": 9804,
    "coordinates": {
      "latitude": "-81.9424",
      "longitude": "-136.8187"
    },
    "timezone": {
      "offset": "+5:45",
      "description": "Kathmandu"
    }
  },
  "email": "tommy.bailey@example.com",
  "login": {
    "uuid": "e0ba96cb-8036-4bb3-b6af-4549b7b9cabb",
    "username": "redzebra339",
    "password": "hassan",
    "salt": "IdmzTTm8",
    "md5": "738adc44015fbcf17e9cb60aecd270d9",
    "sha1": "a9fee94811b9f13556edf31613c67b6f5382abf5",
    "sha256": "5deb3e352c0b0cf1e3942417c9f3f1eabf11f7939faa7252cc7256b69bbb06f0"
  },
  "dob": {
    "date": "1962-08-31T10:37:39.025Z",
    "age": 62
  },
  "registered": {
    "date": "2008-04-28T23:40:12.078Z",
    "age": 16
  },
  "phone": "07-4767-6776",
  "cell": "0438-859-448",
  "id": {
    "name": "TFN",
    "value": "008567321"
  },
  "picture": {
    "large": "https://randomuser.me/api/portraits/men/60.jpg",
    "medium": "https://randomuser.me/api/portraits/med/men/60.jpg",
    "thumbnail": "https://randomuser.me/api/portraits/thumb/men/60.jpg"
  },
  "nat": "AU"
}