{
  "gender": "female",
  "name": {
    "title": "Mrs",
    "first": "Lyna",
    "last": "Gerard"
  },
  "location": {
    "street": {
      "number": 9382,
      "name": "Rue des Ecrivains"
    },
    "city": "Poitiers",
    "state": "Corse-du-Sud",
    "country": "France",
    "postcode": 76183,
    "coordinates": {
      "latitude": "-19.7356",
      "longitude": "151.9621"
    },
    "timezone": {
      "offset": "+8:00",
      "description": "Beijing, Perth, Singapore, Hong Kong"
    }
  },
  "email": "lyna.gerard@example.com",
  "login": {
    "uuid": "a66dfbb3-b7b7-4665-960b-00dea4370817",
    "username": "sadbear125",
    "password": "1414",
    "salt": "BRDAAuMz",
    "md5": "c578d88c720696a4fba372bd7e8e1f3b",
    "sha1": "d13c66dec1bc082ce46efde4aee2aacc354d8714",
    "sha256": "f4b646d3bc29476c940be619ffe653eb76799dceb1f95742d5e0422b82a20071"
  },
  "dob": {
    "date": "1992-04-06T14:36:57.836Z",
    "age": 32
  },
  "registered": {
    "date": "2021-01-17T18:16:19.095Z",
    "age": 4
  },
  "phone": "02-24-05-14-12",
  "cell": "06-99-49-80-05",
  "id": {
    "name": "INSEE",
    "value": "2920360834588 28"
  },
  "picture": {
    "large": "https://randomuser.me/api/portraits/women/62.jpg",
    "medium": "https://randomuser.me/api/portraits/med/women/62.jpg",
    "thumbnail": "https://randomuser.me/api/portraits/thumb/women/62.jpg"
  },
  "nat": "FR"
}