{
  "gender": "male",
  "name": {
    "title": "Mr",
    "first": "Jimmy",
    "last": "Wilson"
  },
  "location": {
    "street": {
      "number": 4137,
      "name": "Rectory Lane"
    },
    "city": "Wolverhampton",
    "state": "Essex",
    "country": "United Kingdom",
    "postcode": "UN5T 9EW",
    "coordinates": {
      "latitude": "-5.4027",
      "longitude": "-102.3119"
    },
    "timezone": {
      "offset": "-8:00",
      "description": "Pacific Time (US & Canada)"
    }
  },
  "email": "jimmy.wilson@example.com",
  "login": {
    "uuid": "7f26bf50-86f1-400d-939c-7c55bf946c80",
    "username": "purplerabbit526",
    "password": "comedy",
    "salt": "GA7ecaYt",
    "md5": "bfc0146375c4b44fa876584d9a6e8ab7",
    "sha1": "9698bcca63f2e62f85cf868a75408e1f81414fca",
    "sha256": "b067eef9f59b56f5affb4af3ef7c0e760a9e6b864adf3e7efaa40f728e7bc8de"
  },
  "dob": {
    "date": "1988-06-12T20:50:08.247Z",
    "age": 36
  },
  "registered": {
    "date": "2009-08-12T06:01:21.564Z",
    "age": 15
  },
  "phone": "016973 15759",
  "cell": "07360 715285",
  "id": {
    "name": "NINO",
    "value": "YB 55 64 27 L"
  },
  "picture": {
    "large": "https://randomuser.me/api/portraits/men/33.jpg",
    "medium": "https://randomuser.me/api/portraits/med/men/33.jpg",
    "thumbnail": "https://randomuser.me/api/portraits/thumb/men/33.jpg"
  },
  "nat": "GB"
}