{
  "gender": "female",
  "name": {
    "title": "Ms",
    "first": "Sara",
    "last": "Pedersen"
  },
  "location": {
    "street": {
      "number": 2546,
      "name": "Hegnet"
    },
    "city": "Snertinge",
    "state": "Danmark",
    "country": "Denmark",
    "postcode": 41836,
    "coordinates": {
      "latitude": "-44.3383",
      "longitude": "141.9853"
    },
    "timezone": {
      "offset": "-10:00",
      "description": "Hawaii"
    }
  },
  "email": "sara.pedersen@example.com",
  "login": {
    "uuid": "cbf144c1-543a-4358-81d2-dbeb1d26b08c",
    "username": "bigswan760",
    "password": "streaming",
    "salt": "qoNntFXh",
    "md5": "1bada75982b8ae9481648e3e969054d9",
    "sha1": "7ea4c17cf8fba97092f0d1667c4cfe4003460ff0",
    "sha256": "07ad4672ee6686547ebe842e2885efec0bc863ab8d04c8068bc947bab1ad04e0"
  },
  "dob": {
    "date": "1996-10-09T20:21:05.698Z",
    "age": 28
  },
  "registered": {
    "date": "2017-01-20T12:46:41.072Z",
    "age": 8
  },
  "phone": "81470572",
  "cell": "48840239",
  "id": {
    "name": "CPR",
    "value": "091096-9120"
  },
  "picture": {
    "large": "https://randomuser.me/api/portraits/women/6.jpg",
    "medium": "https://randomuser.me/api/portraits/med/women/6.jpg",
    "thumbnail": "https://randomuser.me/api/portraits/thumb/women/6.jpg"
  },
  "nat": "DK"
}