{
  "gender": "male",
  "name": {
    "title": "Mr",
    "first": "Velizar",
    "last": "Borjan"
  },
  "location": {
    "street": {
      "number": 9669,
      "name": "Dobrile živanov Stakić"
    },
    "city": "Beočin",
    "state": "Toplica",
    "country": "Serbia",
    "postcode": 21237,
    "coordinates": {
      "latitude": "57.8327",
      "longitude": "-62.6475"
    },
    "timezone": {
      "offset": "-5:00",
      "description": "Eastern Time (US & Canada), Bogota, Lima"
    }
  },
  "email": "velizar.borjan@example.com",
  "login": {
    "uuid": "d13f21e1-99b3-4075-9be0-4823866def05",
    "username": "tinybear372",
    "password": "pokemon",
    "salt": "LJTnbDuh",
    "md5": "7cc48c6b2f529fbbf963ce398166db9f",
    "sha1": "2805fe28c5bed3f998d17952ef35a6564989a321",
    "sha256": "da50c2983ad06792a82956a4c8bc99f7e7f564f09483c27d35ab515340582a10"
  },
  "dob": {
    "date": "1973-05-13T10:47:14.779Z",
    "age": 52
  },
  "registered": {
    "date": "2005-02-03T13:49:15.760Z",
    "age": 20
  },
  "phone": "024-3899-039",
  "cell": "064-9458-906",
  "id": {
    "name": "SID",
    "value": "676154276"
  },
  "picture": {
    "large": "https://randomuser.me/api/portraits/men/20.jpg",
    "medium": "https://randomuser.me/api/portraits/med/men/20.jpg",
    "thumbnail": "https://randomuser.me/api/portraits/thumb/men/20.jpg"
  },
  "nat": "RS"
}