{
  "gender": "female",
  "name": {
    "title": "Ms",
    "first": "Ludmila",
    "last": "Mančić"
  },
  "location": {
    "street": {
      "number": 4031,
      "name": "Mlinska"
    },
    "city": "Kanjiža",
    "state": "Srem",
    "country": "Serbia",
    "postcode": 91868,
    "coordinates": {
      "latitude": "63.1520",
      "longitude": "174.1401"
    },
    "timezone": {
      "offset": "+4:30",
      "description": "Kabul"
    }
  },
  "email": "ludmila.mancic@example.com",
  "login": {
    "uuid": "76ea694d-e4a8-499a-aa93-6e46fb384372",
    "username": "bluegorilla943",
    "password": "monty",
    "salt": "sOGJKPAP",
    "md5": "50183e9b53ea6053e48f0467d770543a",
    "sha1": "02bb4754291c622489b29e52599aca2563a3890e",
    "sha256": "e5f81401d6ef75595aac594fe66c082643af259e3f0d68109b385c8c757ab0e0"
  },
  "dob": {
    "date": "1962-05-07T05:04:00.908Z",
    "age": 62
  },
  "registered": {
    "date": "2010-03-01T18:42:04.845Z",
    "age": 15
  },
  "phone": "032-5214-100",
  "cell": "061-6559-640",
  "id": {
    "name": "SID",
    "value": "288185102"
  },
  "picture": {
    "large": "https://randomuser.me/api/portraits/women/95.jpg",
    "medium": "https://randomuser.me/api/portraits/med/women/95.jpg",
    "thumbnail": "https://randomuser.me/api/portraits/thumb/women/95.jpg"
  },
  "nat": "RS"
}